scapy_socketlogger/__init__.py
scapy_socketlogger/socket_logger.py
scapy_socketlogger-0.0.2.dist-info/METADATA
scapy_socketlogger-0.0.2.dist-info/WHEEL
scapy_socketlogger-0.0.2.dist-info/licenses/LICENSE.md
scapy_socketlogger-0.0.2.dist-info/RECORD
