Metadata-Version: 2.4
Name: scapy-socketlogger
Version: 0.0.2
Summary: Log all traffic going through an Scapy socket to a PCAP file.
Project-URL: Homepage, https://github.com/antoniovazquezblanco/scapy-socketlogger
Project-URL: Bug Tracker, https://github.com/antoniovazquezblanco/scapy-socketlogger/issues
Author-email: Antonio Vázquez Blanco <antoniovazquezblanco@gmail.com>
License: GPL-3.0-only
License-File: LICENSE.md
Keywords: 
Classifier: License :: OSI Approved :: GNU General Public License v3 (GPLv3)
Classifier: Operating System :: OS Independent
Classifier: Programming Language :: Python :: 3
Requires-Python: >=3.0
Requires-Dist: scapy
